review/bot/__init__.py
review/bot/defaults.py
review/bot/exceptions.py
review/bot/gh_interface.py
review/bot/git_interface.py
review/bot/misc.py
review/bot/open_ai_interface.py
review/bot/cli/__init__.py
review/bot/cli/cli.py
review/bot/schema/__init__.py
review/bot/schema/schema.py
review/bot/schema/resources/schema.json
review/bot/schema/resources/suggestion.json
review_bot-0.2.0.dist-info/entry_points.txt
review_bot-0.2.0.dist-info/LICENSE
review_bot-0.2.0.dist-info/WHEEL
review_bot-0.2.0.dist-info/METADATA
review_bot-0.2.0.dist-info/RECORD
