Metadata-Version: 2.1
Name: review-bot
Version: 0.2.0
Summary: A Python library to automatically generate suggestions and improvements for patches in GitHub PRs by leveraging the power of OpenAI.
Author-email: "ANSYS, Inc." <pyansys.core@ansys.com>
Maintainer-email: PyAnsys developers <pyansys.core@ansys.com>
Requires-Python: >=3.8,<4
Classifier: Development Status :: 4 - Beta
Classifier: Programming Language :: Python :: 3.8
Classifier: Programming Language :: Python :: 3.9
Classifier: Programming Language :: Python :: 3.10
Classifier: Programming Language :: Python :: 3.11
Classifier: License :: OSI Approved :: MIT License
Classifier: Operating System :: OS Independent
Requires-Dist: importlib-metadata>=4.0,<5; python_version<='3.8'
Requires-Dist: requests
Requires-Dist: openai>=1,<2
Requires-Dist: jsonschema
Requires-Dist: gitpython
Requires-Dist: ansys_sphinx_theme==0.12.5 ; extra == "doc"
Requires-Dist: numpydoc==1.6.0 ; extra == "doc"
Requires-Dist: Sphinx==7.2.6 ; extra == "doc"
Requires-Dist: sphinx-autoapi==3.0.0 ; extra == "doc"
Requires-Dist: Sphinx-copybutton==0.5.2 ; extra == "doc"
Requires-Dist: pytest==7.4.3 ; extra == "tests"
Requires-Dist: pytest-cov==4.1.0 ; extra == "tests"
Requires-Dist: pytest-retry==1.5.0 ; extra == "tests"
Requires-Dist: requests==2.31.0 ; extra == "tests"
Requires-Dist: openai==1.3.3 ; extra == "tests"
Requires-Dist: jsonschema==4.20.0 ; extra == "tests"
Requires-Dist: gitpython==3.1.40 ; extra == "tests"
Project-URL: Documentation, https://review-bot.docs.pyansys.com
Project-URL: Homepage, https://github.com/ansys/review-bot
Project-URL: Source, https://github.com/ansys/review-bot
Project-URL: Tracker, https://github.com/ansys/review-bot/issues
Provides-Extra: doc
Provides-Extra: tests
